[
 {
  "id": 1,
  "name": "Nappy",
  "surname": "Scherer",
  "username": "marcos",
  "email": "nscherer0@so-net.ne.jp",
  "password": "cYKBOzhS",
  "image": "nscherer0",
  "date": "21/07/1997"
 },
 {
  "id": 2,
  "name": "carlos ",
  "surname": "lopez",
  "username": "carlospe",
  "email": "carlos@gmail.com",
  "password": "123456",
  "date": "1992-07-06"
 },
 {
  "id": 3,
  "name": "Marcos",
  "surname": "perez",
  "username": "marcos",
  "email": "marcos@gmail.com",
  "password": "123456789",
  "date": "1879-05-22"
 }
]